<?xml version="1.0"?>
<!--
/**
 * @package    Leytech_SingleProductCategoryRedirect
 * @author     Chris Nolan (chris@leytech.co.uk)
 * @copyright  Copyright (c) 2017 Leytech
 * @license    https://opensource.org/licenses/MIT  The MIT License  (MIT)
 */
-->
<config>
    <acl>
        <resources>
            <admin>
                <children>
                    <system>
                        <children>
                            <config>
                                <children>
                                    <leytech_singleproductcategoryredirect translate="title" module="leytech_singleproductcategoryredirect">
                                        <title>Leytech Single Product Category Redirect</title>
                                        <sort_order>12190</sort_order>
                                    </leytech_singleproductcategoryredirect>
                                </children>
                            </config>
                        </children>
                    </system>
                </children>
            </admin>
        </resources>
    </acl>
</config>